CHANGES.txt
LICENSE
MANIFEST.in
README.md
requirements.txt
setup.py
app/__init__.py
app/sct_app.py
app/routes/__init__.py
app/routes/sct_routes.py
app/static/OKTA.svg
app/static/login.html
app/static/register.html
app/static/uploads/DUMMY
app/templates/audits.html
app/templates/index.html
app/utilities/__init__.py
app/utilities/sct_env.py
app/utilities/sct_logging.py
app/utilities/sct_mail.py
app/utilities/sct_schedules.py
app/utilities/sct_security.py
app/utilities/sct_user.py
app/utilities/sct_utils.py
docs/.buildinfo
docs/.nojekyll
docs/app.html
docs/app.routes.html
docs/app.utilities.databases.html
docs/app.utilities.html
docs/configuration.html
docs/contribution.html
docs/custom_installation.html
docs/docker_installation.html
docs/genindex.html
docs/index.html
docs/installation.html
docs/modules.html
docs/objects.inv
docs/py-modindex.html
docs/search.html
docs/searchindex.js
docs/usage.html
docs/.doctrees/app.doctree
docs/.doctrees/app.routes.doctree
docs/.doctrees/app.utilities.databases.doctree
docs/.doctrees/app.utilities.doctree
docs/.doctrees/configuration.doctree
docs/.doctrees/contribution.doctree
docs/.doctrees/custom_installation.doctree
docs/.doctrees/docker_installation.doctree
docs/.doctrees/environment.pickle
docs/.doctrees/index.doctree
docs/.doctrees/installation.doctree
docs/.doctrees/modules.doctree
docs/.doctrees/usage.doctree
docs/_sources/app.routes.rst.txt
docs/_sources/app.rst.txt
docs/_sources/app.utilities.databases.rst.txt
docs/_sources/app.utilities.rst.txt
docs/_sources/configuration.rst.txt
docs/_sources/contribution.rst.txt
docs/_sources/custom_installation.rst.txt
docs/_sources/docker_installation.rst.txt
docs/_sources/index.rst.txt
docs/_sources/installation.rst.txt
docs/_sources/modules.rst.txt
docs/_sources/usage.rst.txt
docs/_static/background_b01.png
docs/_static/basic.css
docs/_static/bizstyle.css
docs/_static/bizstyle.js
docs/_static/css3-mediaqueries.js
docs/_static/css3-mediaqueries_src.js
docs/_static/doctools.js
simple_python_crud_tool.egg-info/PKG-INFO
simple_python_crud_tool.egg-info/SOURCES.txt
simple_python_crud_tool.egg-info/dependency_links.txt
simple_python_crud_tool.egg-info/entry_points.txt
simple_python_crud_tool.egg-info/requires.txt
simple_python_crud_tool.egg-info/top_level.txt