Metadata-Version: 2.1
Name: simple-python-crud-tool
Version: 1.0.0
Summary: Simple Python CRUD Tool
Home-page: UNKNOWN
Author: Sankar Mukherjee
Author-email: sanmuk21@gmail.com
License: MIT
Project-URL: Documentation, https://sankamuk.github.io/SimplyPythonCrudTool
Keywords: python flask database crud
Platform: UNKNOWN
Requires-Python: >=3
License-File: LICENSE
